CHANGES.md
MANIFEST.in
README.rst
setup.cfg
setup.py
olap/__init__.py
olap/xmla/KerberosHttpAutheticated.py
olap/xmla/__init__.py
olap/xmla/adapters.py
olap/xmla/connection.py
olap/xmla/formatreader.py
olap/xmla/http.py
olap/xmla/interfaces.py
olap/xmla/requests_kerberosauth.py
olap/xmla/sessions.py
olap/xmla/utils.py
olap/xmla/vs.wsdl
olap/xmla/xmla.py
xmla.egg-info/PKG-INFO
xmla.egg-info/SOURCES.txt
xmla.egg-info/dependency_links.txt
xmla.egg-info/namespace_packages.txt
xmla.egg-info/not-zip-safe
xmla.egg-info/requires.txt
xmla.egg-info/top_level.txt